deepseek_agent/__init__.py
deepseek_agent/agent.py
deepseek_agent/config/Config.py
deepseek_agent/config/__init__.py
deepseek_agent/utils/__init__.py
deepseek_agent/utils/schema/__init__.py
deepseek_agent/utils/schema/generator.py
deepseek_agent/utils/schema/parameter_config.py
deepseek_agent/utils/schema/validator.py
deepseek_calling_functions-0.1.0.dist-info/METADATA
deepseek_calling_functions-0.1.0.dist-info/WHEEL
deepseek_calling_functions-0.1.0.dist-info/top_level.txt
deepseek_calling_functions-0.1.0.dist-info/RECORD
