Metadata-Version: 2.4
Name: deepseek-calling-functions
Version: 0.1.0
Summary: Python client for DeepSeek AI with function calling capabilities
Author-email: CarlosMaroRuiz <221220@ids.upchiapas.edu.mx>
License: MIT
Project-URL: Homepage, https://github.com/CarlosMaroRuiz/DeepSeek_calling-
Project-URL: Bug Tracker, https://github.com/CarlosMaroRuiz/DeepSeek_calling-/issues
Classifier: Programming Language :: Python :: 3
Classifier: License :: OSI Approved :: MIT License
Classifier: Operating System :: OS Independent
Classifier: Development Status :: 4 - Beta
Classifier: Intended Audience :: Developers
Classifier: Topic :: Scientific/Engineering :: Artificial Intelligence
Requires-Python: >=3.8
Requires-Dist: openai>=1.0.0
Requires-Dist: python-dotenv>=0.19.0
Requires-Dist: pandas>=1.3.0
Provides-Extra: dev
Requires-Dist: pytest>=7.0.0; extra == "dev"
Requires-Dist: black>=22.0.0; extra == "dev"
Requires-Dist: isort>=5.10.0; extra == "dev"
